{
    "product": [
        {
            "id": "1",
            "name": "Product 1",
            "count": "22",
            "description": "This is a product description. Checking the overflow",
            "image": "https://media.istockphoto.com/id/1318011733/vector/blueberries-with-green-leaves-vector-seamless-pattern.jpg?s=1024x1024&w=is&k=20&c=FDoebSqGSnr6MHXKUWfF14SJwqbQX6swXaSjl_U0gkw="
        },
        {
            "id": "2",
            "name": "Product 2",
            "count": "18",
            "description": "This is another product description.",
            "image": "https://media.istockphoto.com/id/1318011733/vector/blueberries-with-green-leaves-vector-seamless-pattern.jpg?s=1024x1024&w=is&k=20&c=FDoebSqGSnr6MHXKUWfF14SJwqbQX6swXaSjl_U0gkw="
        },
        {
            "id": "3",
            "name": "Product 3",
            "count": "56",
            "description": "This is a third product description.",
            "image": "https://media.istockphoto.com/id/1318011733/vector/blueberries-with-green-leaves-vector-seamless-pattern.jpg?s=1024x1024&w=is&k=20&c=FDoebSqGSnr6MHXKUWfF14SJwqbQX6swXaSjl_U0gkw="
        },
        {
            "id": "4",
            "name": "Product 4",
            "count": "36",
            "description": "This is a fourth product description.",
            "image": "https://media.istockphoto.com/id/1318011733/vector/blueberries-with-green-leaves-vector-seamless-pattern.jpg?s=1024x1024&w=is&k=20&c=FDoebSqGSnr6MHXKUWfF14SJwqbQX6swXaSjl_U0gkw="
        },
        {
            "id": "5",
            "name": "Product 5",
            "count": "78",
            "description": "This is a fifth product description.",
            "image": "https://media.istockphoto.com/id/1318011733/vector/blueberries-with-green-leaves-vector-seamless-pattern.jpg?s=1024x1024&w=is&k=20&c=FDoebSqGSnr6MHXKUWfF14SJwqbQX6swXaSjl_U0gkw="
        },
        {
            "id": "6",
            "name": "Product 6",
            "count": "44",
            "description": "This is a sixth product description.",
            "image": "https://media.istockphoto.com/id/1318011733/vector/blueberries-with-green-leaves-vector-seamless-pattern.jpg?s=1024x1024&w=is&k=20&c=FDoebSqGSnr6MHXKUWfF14SJwqbQX6swXaSjl_U0gkw="
        },
        {
            "id": "7",
            "name": "Product 7",
            "count": "34",
            "description": "This is a seventh product description.",
            "image": "https://media.istockphoto.com/id/1318011733/vector/blueberries-with-green-leaves-vector-seamless-pattern.jpg?s=1024x1024&w=is&k=20&c=FDoebSqGSnr6MHXKUWfF14SJwqbQX6swXaSjl_U0gkw="
        },
        {
            "id": "8",
            "name": "Product 8",
            "count": "12",
            "description": "This is an eighth product description.",
            "image": "https://media.istockphoto.com/id/1318011733/vector/blueberries-with-green-leaves-vector-seamless-pattern.jpg?s=1024x1024&w=is&k=20&c=FDoebSqGSnr6MHXKUWfF14SJwqbQX6swXaSjl_U0gkw="
        },
        {
            "id": "9",
            "name": "Product 9",
            "count": "57",
            "description": "This is a ninth product description.",
            "image": "https://media.istockphoto.com/id/1318011733/vector/blueberries-with-green-leaves-vector-seamless-pattern.jpg?s=1024x1024&w=is&k=20&c=FDoebSqGSnr6MHXKUWfF14SJwqbQX6swXaSjl_U0gkw="
        },
        {
            "id": "10",
            "name": "Product 10",
            "count": "220",
            "description": "This is a tenth product description.",
            "image": "https://media.istockphoto.com/id/1318011733/vector/blueberries-with-green-leaves-vector-seamless-pattern.jpg?s=1024x1024&w=is&k=20&c=FDoebSqGSnr6MHXKUWfF14SJwqbQX6swXaSjl_U0gkw="
        },
        {
            "id": "11",
            "name": "Product 11",
            "count": "122",
            "description": "This is a eleventh product description.",
            "image": "https://media.istockphoto.com/id/1318011733/vector/blueberries-with-green-leaves-vector-seamless-pattern.jpg?s=1024x1024&w=is&k=20&c=FDoebSqGSnr6MHXKUWfF14SJwqbQX6swXaSjl_U0gkw="
        },
        {
            "id": "12",
            "name": "Product 12",
            "count": "118",
            "description": "This is a twelfth product description.",
            "image": "https://media.istockphoto.com/id/1318011733/vector/blueberries-with-green-leaves-vector-seamless-pattern.jpg?s=1024x1024&w=is&k=20&c=FDoebSqGSnr6MHXKUWfF14SJwqbQX6swXaSjl_U0gkw="
        }
    ],
    "blogs": [
        {"src" : "https://www.instagram.com/p/DEoXBSKhKyV/embed"},
        {"src" : "https://www.instagram.com/p/DEjNywZSz1u/embed"},
        {"src" : "https://www.instagram.com/p/DEXD_0sSHLY/embed"},
        {"src" : "https://www.instagram.com/p/DEWXnFxSuie/embed"},
        {"src" : "https://www.instagram.com/p/DET2Sg6SW3-/embed"}
    ],
    "similarProducts": [
        { 
            "id": "1",
            "img": "https://th.bing.com/th/id/OIP.3V2fvdA6O0fSG6qGMyMeZwHaEo?rs=1&pid=ImgDetMain"
        },
        {
            "id": "2", 
            "img": "https://images.pexels.com/photos/1640772/pexels-photo-1640772.jpeg?cs=srgb&dl=appetizer-bowl-delicious-1640772.jpg&fm=jpg"
        },
        {
            "id": "3",
            "img": "https://images.pexels.com/photos/1128678/pexels-photo-1128678.jpeg?cs=srgb&dl=food-healthy-creative-1128678.jpg&fm=jpg"
        }
    ],
    "cards": [
        {
            "id": "1",
            "img": "https://th.bing.com/th/id/OIP.3V2fvdA6O0fSG6qGMyMeZwHaEo?rs=1&pid=ImgDetMain",
            "title": "Bike helmet with the new brand",
            "description": "Description for Card 1 writing the description to lines to check the overflow",
            "price": "100",
            "originalPrice": "200",
            "rating": "4",
            "reviews": "50",
            "count": 10,
            "wishlist": true,
            "cart": false
        },
        {
            "id": "2",
            "img": "https://images.pexels.com/photos/1640772/pexels-photo-1640772.jpeg?cs=srgb&dl=appetizer-bowl-delicious-1640772.jpg&fm=jpg",
            "title": "Drag for Royal Enfield Interceptor 650 and GT 650 (Pack of Two)",
            "description": "Dyno Approved Performance-Oriented Exhaust Upto 15% Performance Boost Lightweight Exhaust Uniquely designed with 304 Grade Stainless Steel High-Density Silicon Wool imported from the USA with Heat Resistance up to 1600 Degree Removable DB Killer",
            "price": "200",
            "originalPrice": "300",
            "rating": "5",
            "reviews": "40",
            "count": 0,
            "wishlist": false,
            "cart": false
        },
        {
            "id": "3",
            "img": "https://www.garage91.in/wp-content/uploads/2025/02/3_4_1946x.jpg",
            "title": "Card 3",
            "description": "Description for Card 3",
            "price": "300",
            "originalPrice": "400",
            "rating": "3",
            "reviews": "30",
            "count": 30,
            "wishlist": false,
            "cart": false
        },
        {
            "id": "4",
            "img": "https://th.bing.com/th/id/OIP.3V2fvdA6O0fSG6qGMyMeZwHaEo?rs=1&pid=ImgDetMain",
            "title": "Card 4",
            "description": "Description for Card 4",
            "price": "400",
            "originalPrice": "500",
            "rating": "4",
            "reviews": "20",
            "count": 40,
            "wishlist": false,
            "cart": true
        },
        {
            "id": "5",
            "img": "https://images.pexels.com/photos/1640772/pexels-photo-1640772.jpeg?cs=srgb&dl=appetizer-bowl-delicious-1640772.jpg&fm=jpg",
            "title": "Card 5",
            "description": "Description for Card 5",
            "price": "500",
            "originalPrice": "600",
            "rating": "5",
            "reviews": "10",
            "count": 50,
            "wishlist": true,
            "cart": false
        },
        {
            "id": "6",
            "img": "https://www.garage91.in/wp-content/uploads/2025/02/3_4_1946x.jpg",
            "title": "Card 6",
            "description": "Description for Card 6",
            "price": "600",
            "originalPrice": "700",
            "rating": "3",
            "reviews": "60",
            "count": 60,
            "wishlist": true,
            "cart": false
        },
        {
            "id": "7",
            "img": "https://th.bing.com/th/id/OIP.3V2fvdA6O0fSG6qGMyMeZwHaEo?rs=1&pid=ImgDetMain",
            "title": "Card 7",
            "description": "Description for Card 7",
            "price": "700",
            "originalPrice": "800",
            "rating": "4",
            "reviews": "720",
            "count": 70,
            "wishlist": false,
            "cart": true
        },
        {
            "id": "8",
            "img": "https://images.pexels.com/photos/1640772/pexels-photo-1640772.jpeg?cs=srgb&dl=appetizer-bowl-delicious-1640772.jpg&fm=jpg",
            "title": "Card 8",
            "description": "Description for Card 8",
            "price": "800",
            "originalPrice": "900",
            "rating": "5",
            "reviews": "80",
            "count": 80,
            "wishlist": false,
            "cart": false
        },
        {
            "id": "9",
            "img": "https://www.garage91.in/wp-content/uploads/2025/02/3_4_1946x.jpg",
            "title": "Card 9",
            "description": "Description for Card 9",
            "price": "900",
            "originalPrice": "1000",
            "rating": "3",
            "reviews": "90",
            "count": 90,
            "wishlist": false,
            "cart": false
        },
        {
            "id": "10",
            "img": "https://th.bing.com/th/id/OIP.3V2fvdA6O0fSG6qGMyMeZwHaEo?rs=1&pid=ImgDetMain",
            "title": "Card 10",
            "description": "Description for Card 10",
            "price": "1000",
            "originalPrice": "1100",
            "rating": "4",
            "reviews": "220",
            "count": 100,
            "wishlist": true,
            "cart": false
        },
        {
            "id": "11",
            "img": "https://images.pexels.com/photos/1640772/pexels-photo-1640772.jpeg?cs=srgb&dl=appetizer-bowl-delicious-1640772.jpg&fm=jpg",
            "title": "Card 11",
            "description": "Description for Card 11",
            "price": "1100",
            "originalPrice": "1200",
            "rating": "5",
            "reviews": "110",
            "count": 110,
            "wishlist": false,
            "cart": true
        },
        {
            "id": "12",
            "img": "https://www.garage91.in/wp-content/uploads/2025/02/3_4_1946x.jpg",
            "title": "Card 12",
            "description": "Description for Card 12",
            "price": "1200",
            "originalPrice": "1300",
            "rating": "3",
            "reviews": "120",
            "count": 120,
            "wishlist": false,
            "cart": false
        },
        {
            "id": "13",
            "img": "https://th.bing.com/th/id/OIP.3V2fvdA6O0fSG6qGMyMeZwHaEo?rs=1&pid=ImgDetMain",
            "title": "Card 13",
            "description": "Description for Card 13",
            "price": "1300",
            "originalPrice": "1400",
            "rating": "4",
            "reviews": "130",
            "count": 130,
            "wishlist": false,
            "cart": false
        },
        {
            "id": "14",
            "img": "https://images.pexels.com/photos/1640772/pexels-photo-1640772.jpeg?cs=srgb&dl=appetizer-bowl-delicious-1640772.jpg&fm=jpg",
            "title": "Card 14",
            "description": "Description for Card 14",
            "price": "1400",
            "originalPrice": "1500",
            "rating": "5",
            "reviews": "140",
            "count": 140,
            "wishlist": false,
            "cart": false
        },
        {
            "id": "15",
            "img": "https://www.garage91.in/wp-content/uploads/2025/02/3_4_1946x.jpg",
            "title": "Card 15",
            "description": "Description for Card 15",
            "price": "1500",
            "originalPrice": "1600",
            "rating": "3",
            "reviews": "150",
            "count": 150,
            "wishlist": false,
            "cart": false
        },
        {
            "id": "16",
            "img": "https://th.bing.com/th/id/OIP.3V2fvdA6O0fSG6qGMyMeZwHaEo?rs=1&pid=ImgDetMain",
            "title": "Card 16",
            "description": "Description for Card 16",
            "price": "1600",
            "originalPrice": "1700",
            "rating": "4",
            "reviews": "160",
            "count": 160,
            "wishlist": false,
            "cart": false
        },
        {
            "id": "17",
            "img": "https://images.pexels.com/photos/1640772/pexels-photo-1640772.jpeg?cs=srgb&dl=appetizer-bowl-delicious-1640772.jpg&fm=jpg",
            "title": "Card 17",
            "description": "Description for Card 17",
            "price": "1700",
            "originalPrice": "1800",
            "rating": "5",
            "reviews": "170",
            "count": 170,
            "wishlist": false,
            "cart": false
        },
        {
            "id": "18",
            "img": "https://www.garage91.in/wp-content/uploads/2025/02/3_4_1946x.jpg",
            "title": "Card 18",
            "description": "Description for Card 18",
            "price": "1800",
            "originalPrice": "1900",
            "rating": "3",
            "reviews": "90",
            "count": 180,
            "wishlist": false,
            "cart": false
        },
        {
            "id": "19",
            "img": "https://th.bing.com/th/id/OIP.3V2fvdA6O0fSG6qGMyMeZwHaEo?rs=1&pid=ImgDetMain",
            "title": "Card 19",
            "description": "Description for Card 19",
            "price": "1900",
            "originalPrice": "2000",
            "rating": "4",
            "reviews": "90",
            "count": 190,
            "wishlist": false,
            "cart": false
        },
        {
            "id": "20",
            "img": "https://images.pexels.com/photos/1640772/pexels-photo-1640772.jpeg?cs=srgb&dl=appetizer-bowl-delicious-1640772.jpg&fm=jpg",
            "title": "Card 20",
            "description": "Description for Card 20",
            "price": "2000",
            "originalPrice": "2100",
            "rating": "5",
            "reviews": "200",
            "count": 200,
            "wishlist": false,
            "cart": false
        }
    ]
}